minidump_enums.py
minidump_structs.py
minidump_writer.py
minidumpwriter-1.1.dist-info/LICENSE
minidumpwriter-1.1.dist-info/METADATA
minidumpwriter-1.1.dist-info/WHEEL
minidumpwriter-1.1.dist-info/top_level.txt
minidumpwriter-1.1.dist-info/RECORD
