Metadata-Version: 2.1
Name: minidumpwriter
Version: 1.1
Summary: Minidump writer
Home-page: https://github.com/paulkermann/MinidumpWriter
Author: Paul Kermann
Author-email: paulkermann@tutanota.com
License-File: LICENSE
